deepsearcher/__init__.py
deepsearcher/cli.py
deepsearcher/config.yaml
deepsearcher/configuration.py
deepsearcher/offline_loading.py
deepsearcher/online_query.py
deepsearcher/agent/__init__.py
deepsearcher/agent/base.py
deepsearcher/agent/chain_of_rag.py
deepsearcher/agent/collection_router.py
deepsearcher/agent/deep_search.py
deepsearcher/agent/naive_rag.py
deepsearcher/agent/rag_router.py
deepsearcher/embedding/__init__.py
deepsearcher/embedding/base.py
deepsearcher/embedding/bedrock_embedding.py
deepsearcher/embedding/fastembed_embdding.py
deepsearcher/embedding/gemini_embedding.py
deepsearcher/embedding/glm_embedding.py
deepsearcher/embedding/milvus_embedding.py
deepsearcher/embedding/novita_embedding.py
deepsearcher/embedding/ollama_embedding.py
deepsearcher/embedding/openai_embedding.py
deepsearcher/embedding/ppio_embedding.py
deepsearcher/embedding/sentence_transformer_embedding.py
deepsearcher/embedding/siliconflow_embedding.py
deepsearcher/embedding/volcengine_embedding.py
deepsearcher/embedding/voyage_embedding.py
deepsearcher/llm/__init__.py
deepsearcher/llm/aliyun.py
deepsearcher/llm/anthropic_llm.py
deepsearcher/llm/azure_openai.py
deepsearcher/llm/base.py
deepsearcher/llm/bedrock.py
deepsearcher/llm/deepseek.py
deepsearcher/llm/gemini.py
deepsearcher/llm/glm.py
deepsearcher/llm/novita.py
deepsearcher/llm/ollama.py
deepsearcher/llm/openai_llm.py
deepsearcher/llm/ppio.py
deepsearcher/llm/siliconflow.py
deepsearcher/llm/together_ai.py
deepsearcher/llm/volcengine.py
deepsearcher/llm/xai.py
deepsearcher/loader/__init__.py
deepsearcher/loader/splitter.py
deepsearcher/loader/file_loader/__init__.py
deepsearcher/loader/file_loader/base.py
deepsearcher/loader/file_loader/docling_loader.py
deepsearcher/loader/file_loader/json_loader.py
deepsearcher/loader/file_loader/pdf_loader.py
deepsearcher/loader/file_loader/text_loader.py
deepsearcher/loader/file_loader/unstructured_loader.py
deepsearcher/loader/web_crawler/__init__.py
deepsearcher-0.0.2.dist-info/METADATA
deepsearcher-0.0.2.dist-info/WHEEL
deepsearcher-0.0.2.dist-info/entry_points.txt
deepsearcher-0.0.2.dist-info/licenses/LICENSE
deepsearcher-0.0.2.dist-info/RECORD
