Metadata-Version: 2.4
Name: deepsearcher
Version: 0.0.2
Summary: None
Project-URL: Homepage, https://github.com/zilliztech/deep-searcher
Author-email: Cheney Zhang <277584121@qq.com>, SimFG <bang.fu@zilliz.com>
License:                                  Apache License
License-File: LICENSE
Requires-Python: >=3.10
Requires-Dist: argparse>=1.4.0
Requires-Dist: fastapi>=0.115.12
Requires-Dist: firecrawl-py>=2.5.3
Requires-Dist: langchain-text-splitters>=0.3.8
Requires-Dist: numpy>=1.26.4
Requires-Dist: openai>=1.77.0
Requires-Dist: pdfplumber>=0.11.6
Requires-Dist: pymilvus>=2.5.8
Requires-Dist: requests>=2.32.3
Requires-Dist: termcolor>=3.1.0
Requires-Dist: tqdm>=4.67.1
Requires-Dist: uvicorn>=0.34.2
Provides-Extra: all
Requires-Dist: anthropic>=0.51.0; extra == 'all'
Requires-Dist: azure-search-documents>=11.5.2; extra == 'all'
Requires-Dist: boto3>=1.38.11; extra == 'all'
Requires-Dist: crawl4ai>=0.6.2; extra == 'all'
Requires-Dist: docling-core>=2.30.0; extra == 'all'
Requires-Dist: docling>=2.15.1; extra == 'all'
Requires-Dist: fastembed>=0.6.1; extra == 'all'
Requires-Dist: google-genai>=1.14.0; extra == 'all'
Requires-Dist: ollama>=0.4.8; extra == 'all'
Requires-Dist: oracledb>=3.1.0; extra == 'all'
Requires-Dist: qdrant-client>=1.14.2; extra == 'all'
Requires-Dist: sentence-transformers>=4.1.0; extra == 'all'
Requires-Dist: together>=1.3.14; extra == 'all'
Requires-Dist: unstructured-ingest>=1.0.24; extra == 'all'
Requires-Dist: unstructured[all-docs]>=0.17.2; extra == 'all'
Requires-Dist: voyageai>=0.3.2; extra == 'all'
Requires-Dist: zhipuai>=2.1.5.20250421; extra == 'all'
Provides-Extra: anthropic
Requires-Dist: anthropic>=0.51.0; extra == 'anthropic'
Provides-Extra: azure-search
Requires-Dist: azure-search-documents>=11.5.2; extra == 'azure-search'
Provides-Extra: boto3
Requires-Dist: boto3>=1.38.11; extra == 'boto3'
Provides-Extra: crawl4ai
Requires-Dist: crawl4ai>=0.6.2; extra == 'crawl4ai'
Provides-Extra: docling
Requires-Dist: docling-core>=2.30.0; extra == 'docling'
Requires-Dist: docling>=2.15.1; extra == 'docling'
Provides-Extra: google
Requires-Dist: google-genai>=1.14.0; extra == 'google'
Provides-Extra: ollama
Requires-Dist: ollama>=0.4.8; extra == 'ollama'
Provides-Extra: oracledb
Requires-Dist: oracledb>=3.1.0; extra == 'oracledb'
Provides-Extra: qdrant
Requires-Dist: fastembed>=0.6.1; extra == 'qdrant'
Requires-Dist: qdrant-client>=1.14.2; extra == 'qdrant'
Provides-Extra: sentence-transformers
Requires-Dist: sentence-transformers>=4.1.0; extra == 'sentence-transformers'
Provides-Extra: together
Requires-Dist: together>=1.3.14; extra == 'together'
Provides-Extra: unstructured
Requires-Dist: unstructured-ingest>=1.0.24; extra == 'unstructured'
Requires-Dist: unstructured[all-docs]>=0.17.2; extra == 'unstructured'
Provides-Extra: voyageai
Requires-Dist: voyageai>=0.3.2; extra == 'voyageai'
Provides-Extra: zhipuai
Requires-Dist: zhipuai>=2.1.5.20250421; extra == 'zhipuai'
